handshake_client/chain.py
handshake_client/constant.py
handshake_client/http_.py
handshake_client/rpc.py
handshake_client/sockets.py
handshake_client-0.1.7.dist-info/LICENSE
handshake_client-0.1.7.dist-info/WHEEL
handshake_client-0.1.7.dist-info/METADATA
handshake_client-0.1.7.dist-info/RECORD
